<diffgr:diffgram xmlns:msdata="urn:schemas-microsoft-com:xml-msdata" xmlns:diffgr="urn:schemas-microsoft-com:xml-diffgram-v1">
  <DSPROJECT>
    <D_Project diffgr:id="D_Project1" msdata:rowOrder="0" diffgr:hasChanges="inserted">
      <iID>1</iID>
      <szName>18-502</szName>
      <dtCreateDate>2018-06-21T08:59:10.1485602+08:00</dtCreateDate>
      <iProjectAttributeID>1</iProjectAttributeID>
      <bUserManage>false</bUserManage>
    </D_Project>
    <D_Project diffgr:id="D_Project2" msdata:rowOrder="1" diffgr:hasChanges="inserted">
      <iID>2</iID>
      <szName>18-502_20180719</szName>
      <dtCreateDate>2018-07-19T10:20:49.8998094+08:00</dtCreateDate>
      <iProjectAttributeID>1</iProjectAttributeID>
      <bUserManage>false</bUserManage>
    </D_Project>
    <D_Project diffgr:id="D_Project3" msdata:rowOrder="2" diffgr:hasChanges="inserted">
      <iID>3</iID>
      <szName>18-502_20180802</szName>
      <dtCreateDate>2018-08-02T09:08:14.1636581+08:00</dtCreateDate>
      <iProjectAttributeID>1</iProjectAttributeID>
      <bUserManage>false</bUserManage>
    </D_Project>
    <D_Project diffgr:id="D_Project4" msdata:rowOrder="3" diffgr:hasChanges="inserted">
      <iID>4</iID>
      <szName>18-502_20180808</szName>
      <dtCreateDate>2018-08-08T10:23:27.9869548+08:00</dtCreateDate>
      <iProjectAttributeID>1</iProjectAttributeID>
      <bUserManage>false</bUserManage>
    </D_Project>
    <D_DBVersion diffgr:id="D_DBVersion2" msdata:rowOrder="0" diffgr:hasChanges="inserted">
      <iSupportVersion>1</iSupportVersion>
      <iCreateVersion>1</iCreateVersion>
    </D_DBVersion>
  </DSPROJECT>
</diffgr:diffgram>